gym_update1/__init__.py
gym_update1/envs/__init__.py
gym_update1/envs/update_env1.py
gym_update1-0.0.7.dist-info/LICENSE
gym_update1-0.0.7.dist-info/METADATA
gym_update1-0.0.7.dist-info/WHEEL
gym_update1-0.0.7.dist-info/top_level.txt
gym_update1-0.0.7.dist-info/RECORD
