Metadata-Version: 2.1
Name: gym-update1
Version: 0.0.7
Summary: A OpenAI Gym Env for continuous control
Home-page: UNKNOWN
Author: Claudia Viaro
License: MIT
Platform: UNKNOWN
Requires-Dist: gym
